[
  {
    "id": 1,
    "name": "AT 298 Ivatan",
    "dbName": "AT 298 Ivatan [Balikpapan]",
    "comments": "Ex AU. X2, +3",
    "type": "LCU - Utility Landing Craft",
    "operator": "Navy",
    "commissioned": 2015,
    "crew": 14,
    "displacementFull": 503,
    "length": 44.5,
    "beam": 10.1,
    "draft": 1.9,
    "maxDepth": null,
    "sensorCount": 1,
    "weaponCount": 1,
    "description": "AT 298 Ivatan [Ex AU. X2, +3]"
  },
  {
    "id": 2,
    "name": "LC 550 Bacolod City",
    "dbName": "LC 550 Bacolod City [Besson]",
    "comments": "2x",
    "type": "LSV - Vehicle Landing Ship ",
    "operator": "Navy",
    "commissioned": 1993,
    "crew": 44,
    "displacementFull": 4199,
    "length": 83,
    "beam": 18.28,
    "draft": 1.75,
    "maxDepth": null,
    "sensorCount": 1,
    "weaponCount": 1,
    "description": "LC 550 Bacolod City [2x]"
  },
  {
    "id": 3,
    "name": "LD 601 Tarlac",
    "dbName": "LD 601 Tarlac [Makassar Class]",
    "comments": "SSV Program, 2x LCU,",
    "type": "LPD - Amphibious Transport Dock Vessel",
    "operator": "Navy",
    "commissioned": 2017,
    "crew": 120,
    "displacementFull": 11580,
    "length": 122,
    "beam": 22,
    "draft": 4.9,
    "maxDepth": null,
    "sensorCount": 2,
    "weaponCount": 1,
    "description": "LD 601 Tarlac [SSV Program, 2x LCU,]"
  },
  {
    "id": 4,
    "name": "PF 11 Rajah Humabon",
    "dbName": "PF 11 Rajah Humabon [Cannon Class]",
    "comments": "Renamed, PF 6 until 1995",
    "type": "DE - Destroyer Escort",
    "operator": "Navy",
    "commissioned": 1977,
    "crew": 165,
    "displacementFull": 1750,
    "length": 93.3,
    "beam": 11.2,
    "draft": 3.6,
    "maxDepth": null,
    "sensorCount": 3,
    "weaponCount": 3,
    "description": "PF 11 Rajah Humabon [Renamed, PF 6 until 1995]"
  },
  {
    "id": 5,
    "name": "PF 15 Gregorio del Pilar",
    "dbName": "PF 15 Gregorio del Pilar [Hamilton Class]",
    "comments": "Mk38 Mod 2",
    "type": "WHEC - Coast Guard High Endurance Cutter",
    "operator": "Navy",
    "commissioned": 2014,
    "crew": 177,
    "displacementFull": 3050,
    "length": 115.4,
    "beam": 13.1,
    "draft": 4.3,
    "maxDepth": null,
    "sensorCount": 4,
    "weaponCount": 7,
    "description": "PF 15 Gregorio del Pilar [Mk38 Mod 2]"
  },
  {
    "id": 6,
    "name": "PF 6 Rajah Humabon",
    "dbName": "PF 6 Rajah Humabon [Cannon Class]",
    "comments": "-",
    "type": "DE - Destroyer Escort",
    "operator": "Navy",
    "commissioned": 1997,
    "crew": 165,
    "displacementFull": 1750,
    "length": 93.3,
    "beam": 11.2,
    "draft": 3.6,
    "maxDepth": null,
    "sensorCount": 1,
    "weaponCount": 3,
    "description": "PF 6 Rajah Humabon"
  },
  {
    "id": 7,
    "name": "PG 110 Tomas Batillo",
    "dbName": "PG 110 Tomas Batillo [Sea Dolphin]",
    "comments": "x8",
    "type": "PG - Patrol Gunboat",
    "operator": "Navy",
    "commissioned": 1996,
    "crew": 31,
    "displacementFull": 144,
    "length": 33.1,
    "beam": 6.9,
    "draft": 1.8,
    "maxDepth": null,
    "sensorCount": 1,
    "weaponCount": 5,
    "description": "PG 110 Tomas Batillo [x8]"
  },
  {
    "id": 8,
    "name": "PG 140 Emilio Aguinaldo",
    "dbName": "PG 140 Emilio Aguinaldo",
    "comments": "-",
    "type": "PC - Coastal Patrol Boat",
    "operator": "Navy",
    "commissioned": 1992,
    "crew": 58,
    "displacementFull": 279,
    "length": 44,
    "beam": 6.2,
    "draft": 1.6,
    "maxDepth": null,
    "sensorCount": 2,
    "weaponCount": 4,
    "description": "PG 140 Emilio Aguinaldo"
  },
  {
    "id": 9,
    "name": "PG 370 Jose Andrada",
    "dbName": "PG 370 Jose Andrada",
    "comments": "-",
    "type": "PG - Patrol Gunboat",
    "operator": "Navy",
    "commissioned": 1998,
    "crew": 10,
    "displacementFull": 56,
    "length": 23.7,
    "beam": 6.1,
    "draft": 1,
    "maxDepth": null,
    "sensorCount": 2,
    "weaponCount": 4,
    "description": "PG 370 Jose Andrada"
  },
  {
    "id": 10,
    "name": "PG 61 Agusan",
    "dbName": "PG 61 Agusan [PGM 39 Class]",
    "comments": "ex-US PGM 39",
    "type": "PG - Patrol Gunboat",
    "operator": "Navy",
    "commissioned": 1960,
    "crew": 15,
    "displacementFull": 122,
    "length": 30.6,
    "beam": 6.4,
    "draft": 2.1,
    "maxDepth": null,
    "sensorCount": 1,
    "weaponCount": 1,
    "description": "PG 61 Agusan [ex-US PGM 39]"
  },
  {
    "id": 11,
    "name": "PS 19 Miguel Malvar",
    "dbName": "PS 19 Miguel Malvar [PCE(R)-848]",
    "comments": "-",
    "type": "FFL - Corvette",
    "operator": "Navy",
    "commissioned": 1992,
    "crew": 77,
    "displacementFull": 914,
    "length": 56.2,
    "beam": 10,
    "draft": 3,
    "maxDepth": null,
    "sensorCount": 2,
    "weaponCount": 4,
    "description": "PS 19 Miguel Malvar"
  },
  {
    "id": 12,
    "name": "PS 20 Magat Salamat",
    "dbName": "PS 20 Magat Salamat [Admirable]",
    "comments": "-",
    "type": "FFL - Corvette",
    "operator": "Navy",
    "commissioned": 1993,
    "crew": 77,
    "displacementFull": 914,
    "length": 56.2,
    "beam": 10,
    "draft": 3,
    "maxDepth": null,
    "sensorCount": 2,
    "weaponCount": 4,
    "description": "PS 20 Magat Salamat"
  },
  {
    "id": 13,
    "name": "PS 35 Emilio Jacinto",
    "dbName": "PS 35 Emilio Jacinto [Peacock]",
    "comments": "-",
    "type": "PB - Patrol Boat",
    "operator": "Navy",
    "commissioned": 2006,
    "crew": 31,
    "displacementFull": 763,
    "length": 62.6,
    "beam": 10,
    "draft": 2.7,
    "maxDepth": null,
    "sensorCount": 2,
    "weaponCount": 4,
    "description": "PS 35 Emilio Jacinto"
  },
  {
    "id": 14,
    "name": "PS 38 General Mariano Alvarez",
    "dbName": "PS 38 General Mariano Alvarez [Cyclone]",
    "comments": "-ex USS Cyclone",
    "type": "PC - Coastal Patrol Boat",
    "operator": "Navy",
    "commissioned": 2001,
    "crew": 28,
    "displacementFull": 336,
    "length": 52.8,
    "beam": 7.6,
    "draft": 2.4,
    "maxDepth": null,
    "sensorCount": 7,
    "weaponCount": 6,
    "description": "PS 38 General Mariano Alvarez [-ex USS Cyclone]"
  },
  {
    "id": 15,
    "name": "PS 69 Rizal",
    "dbName": "PS 69 Rizal [Auk Class]",
    "comments": "Renamed PS 70 after upgrade",
    "type": "FFL - Corvette",
    "operator": "Navy",
    "commissioned": 1966,
    "crew": 100,
    "displacementFull": 1250,
    "length": 67.4,
    "beam": 9.8,
    "draft": 3.3,
    "maxDepth": null,
    "sensorCount": 2,
    "weaponCount": 2,
    "description": "PS 69 Rizal [Renamed PS 70 after upgrade]"
  },
  {
    "id": 16,
    "name": "PS 70 Rizal",
    "dbName": "PS 70 Rizal [Auk Class, Upgrade]",
    "comments": "Ex-PS 69",
    "type": "FFL - Corvette",
    "operator": "Navy",
    "commissioned": 1997,
    "crew": 100,
    "displacementFull": 1250,
    "length": 67.4,
    "beam": 9.8,
    "draft": 3.3,
    "maxDepth": null,
    "sensorCount": 2,
    "weaponCount": 2,
    "description": "PS 70 Rizal [Ex-PS 69]"
  }
]