{
  "aircraft": {
    "1": "McDonnell_Douglas_A-4_Skyhawk",
    "2": "Boeing_AH-64_Apache",
    "3": "Tethered_Aerostat_Radar_System",
    "4": "McDonnell_Douglas_C-9",
    "5": "Eurofighter_Typhoon",
    "6": "Eurofighter_Typhoon",
    "7": "McDonnell_Douglas_F/A-18_Hornet",
    "8": "McDonnell_Douglas_F/A-18_Hornet",
    "9": "Dassault_Mirage_F1",
    "10": "Dassault_Mirage_F1",
    "11": "Aerospatiale_SA_330_Puma",
    "12": "Eurocopter_AS332",
    "13": "Aérospatiale_Gazelle",
    "14": "McDonnell_Douglas_A-4_Skyhawk"
  },
  "ships": {
    "1": "Kuwait_Naval_Force",
    "2": "Kuwait_Naval_Force",
    "3": "Kuwait_Naval_Force"
  },
  "weapons": {
    "1": "Naval_gun",
    "2": "Naval_gun",
    "3": "M2_Browning",
    "4": "Rheinmetall_Rh-120",
    "5": "Autocannon",
    "6": "Torpedo",
    "7": "Torpedo",
    "8": "OTO_Melara_76_mm",
    "9": "Torpedo",
    "10": "Air-to-surface_missile",
    "11": "Electronic_warfare",
    "12": "Sonobuoy",
    "13": "Sonobuoy",
    "14": "Sonobuoy",
    "15": "Anti-ship_missile",
    "16": "Anti-ship_missile",
    "17": "Anti-ship_missile",
    "18": "Anti-ship_missile",
    "19": "Anti-ship_missile",
    "20": "Targeting_pod",
    "21": "Intercontinental_ballistic_missile",
    "22": "Intercontinental_ballistic_missile",
    "23": "Ballistic_missile",
    "24": "Ballistic_missile",
    "25": "Anti-tank_guided_missile",
    "26": "Surface-to-air_missile",
    "27": "Surface-to-air_missile",
    "28": "Silkworm_(missile)",
    "29": "Silkworm_(missile)",
    "30": "Ballistic_missile",
    "31": "Cruise_missile",
    "32": "Paveway",
    "33": "Submarine-launched_ballistic_missile",
    "34": "Pershing_II",
    "35": "Torpedo",
    "36": "Crotale_(missile)",
    "37": "Crotale_(missile)",
    "38": "Crotale_(missile)",
    "39": "Sonobuoy",
    "40": "AIM-7_Sparrow",
    "41": "S-13_rocket",
    "42": "S-8_(rocket)",
    "43": "S-8_(rocket)",
    "44": "Scud",
    "45": "Silkworm_(missile)",
    "46": "Unha",
    "47": "YJ-8"
  },
  "sensors": {
    "1": "Fire-control_radar",
    "2": "Electro-optical_targeting_system",
    "3": "Missile_approach_warning_system",
    "4": "Electronic_countermeasure",
    "5": "Barrage_jamming",
    "6": "Electronic_countermeasure",
    "7": "Radar_warning_receiver",
    "8": "Radar_warning_receiver",
    "9": "Pulse-Doppler_radar",
    "10": "Active_electronically_scanned_array",
    "11": "Pulse-Doppler_radar",
    "12": "Signals_intelligence",
    "13": "AN/FPS-117",
    "14": "Airport_surveillance_radar",
    "15": "Airport_surveillance_radar",
    "16": "Airport_surveillance_radar",
    "17": "Electronic_intelligence",
    "18": "Forward-looking_infrared",
    "19": "Active_electronically_scanned_array",
    "20": "Electronic_intelligence",
    "21": "Sonar",
    "22": "Pulse-Doppler_radar",
    "23": "Electronic_countermeasure",
    "24": "Electronic_countermeasure",
    "25": "Electronic_countermeasure",
    "26": "Electronic_countermeasure",
    "27": "Decca_Radar",
    "28": "Decca_Radar",
    "29": "Decca_Radar",
    "30": "Electronic_intelligence",
    "31": "Electronic_intelligence",
    "32": "Laser_designator",
    "33": "Weather_radar",
    "34": "Combat_information_center",
    "35": "Fire-control_radar",
    "36": "Fire-control_radar",
    "37": "Marine_radar",
    "38": "Electro-optical_targeting_system",
    "39": "Thales_Herakles",
    "40": "Infrared_search_and_track",
    "41": "Doppler_radar",
    "42": "Giraffe_radar",
    "43": "Marine_radar",
    "44": "Pulse-Doppler_radar",
    "45": "Pulse-Doppler_radar",
    "46": "Combat_information_center",
    "47": "Doppler_radar"
  },
  "infantry": {
    "2": "Infantry"
  },
  "armor": {
    "3": "Warrior_infantry_fighting_vehicle"
  },
  "artillery": {},
  "airdefense": {
    "12": "MIM-23_Hawk",
    "13": "MIM-23_Hawk",
    "14": "MIM-104_Patriot",
    "15": "MIM-104_Patriot",
    "16": "Aspide_(missile)",
    "17": "Aspide_(missile)"
  },
  "radar": {}
}