[
  {
    "id": 1,
    "name": "Radar (AN/TPS-77)",
    "dbName": "Radar (AN/TPS-77)",
    "comments": "1x",
    "type": "Mobile Vehicle(s)",
    "operator": "Air Force",
    "commissioned": 2004,
    "crew": 0,
    "length": 4,
    "width": 6,
    "damagePoints": 1,
    "sensorCount": 1,
    "weaponCount": 0,
    "description": "Radar (AN/TPS-77) [1x]"
  },
  {
    "id": 2,
    "name": "Radar (ASR-7 GCA)",
    "dbName": "Radar (ASR-7 GCA)",
    "comments": "1x",
    "type": "Building (Surface)",
    "operator": "Air Force",
    "commissioned": 2003,
    "crew": 0,
    "length": 12,
    "width": 12,
    "damagePoints": 1,
    "sensorCount": 1,
    "weaponCount": 0,
    "description": "Radar (ASR-7 GCA) [1x]"
  },
  {
    "id": 3,
    "name": "Radar (Giraffe 40)",
    "dbName": "Radar (Giraffe 40)",
    "comments": "1x",
    "type": "Mobile Vehicle(s)",
    "operator": "Army",
    "commissioned": 2008,
    "crew": 0,
    "length": 4,
    "width": 6,
    "damagePoints": 1,
    "sensorCount": 1,
    "weaponCount": 0,
    "description": "Radar (Giraffe 40) [1x]"
  },
  {
    "id": 4,
    "name": "SAM Plt (RBS 70 Mk1 MANPADS x 3)",
    "dbName": "SAM Plt (RBS 70 Mk1 MANPADS x 3)",
    "comments": "Ex-Swedish, 2x + Giraffe 40 pr Bty, 6x Bty",
    "type": "Mobile Personnel",
    "operator": "Army",
    "commissioned": 2008,
    "crew": 1,
    "length": 0,
    "width": 0,
    "damagePoints": 0,
    "sensorCount": 0,
    "weaponCount": 1,
    "description": "SAM Plt (RBS 70 Mk1 MANPADS x 3) [Ex-Swedish, 2x + Giraffe 40 pr Bty, 6x Bty]"
  }
]